{
    "data":[
        {
            "id":"1",
            "text":"Anak Pertama"
        },
        {
            "id":"2",
            "text":"Anak Kedua"
        },
        {
            "id":"3",
            "text":"Anak Ketiga"
        },
        {
            "id":"4",
            "text":"Anak Keempat"
        },
        {
            "id":"5",
            "text":"Anak Kelima"
        },
        {
            "id":"6",
            "text":"Anak Keenam"
        },
        {
            "id":"7",
            "text":"Anak Ketujuh"
        },
        {
            "id":"8",
            "text":"Anak Kedelapan"
        },
        {
            "id":"9",
            "text":"Anak Kesembilan"
        },
        {
            "id":"10",
            "text":"Anak Kesepuluh"
        },
        {
            "id":"11",
            "text":"Anak Kesebelas"
        },
        {
            "id":"12",
            "text":"Anak Kedua Belas"
        },
        {
            "id":"13",
            "text":"Anak Ketiga Belas"
        },
        {
            "id":"14",
            "text":"Anak Keempat Belas"
        },
        {
            "id":"15",
            "text":"Anak Kelima Belas"
        },
        {
            "id":"16",
            "text":"Anak Keenam Belas"
        },
        {
            "id":"17",
            "text":"Anak Ketujuh Belas"
        },
        {
            "id":"18",
            "text":"Anak Kedelapan Belas"
        },
        {
            "id":"19",
            "text":"Anak Kesembilan Belas"
        },
        {
            "id":"20",
            "text":"Anak Keduapuluh"
        }
    ]
}
